rsg/__init__.py
rsg/core.py
rsg/utils/__init__.py
rsg/utils/helpers.py
rsg-0.1.1.dist-info/LICENSE.txt
rsg-0.1.1.dist-info/METADATA
rsg-0.1.1.dist-info/WHEEL
rsg-0.1.1.dist-info/top_level.txt
rsg-0.1.1.dist-info/RECORD
