Metadata-Version: 2.1
Name: rsg
Version: 0.1.1
Summary: Random Structure Generator
Home-page: https://github.com/lucabonfiglioli/rsg
Author: Luca Bonfiglioli
Author-email: Luca.Bonfiglioli@gmail.com
License: GNU General Public License v3.0
Keywords: rng,random,structure,generator,rsg,deep,nested,composite,tree,recursive
Platform: UNKNOWN
Requires-Python: >=3.9
License-File: LICENSE.txt
